design.sv
// Code your design here
module ALU(
  input [7:0] A, B,
  input [3:0] ALU_Sel,
  output [7:0] ALU_Out,
  output CarryOut
);
  reg[7:0] ALU_Res;
  wire[8:0] temp;
  assign temp = {1'b0,A} + {1'b0,B};
  assign CarryOut = temp[8];
  assign ALU_Out = ALU_Res;
  
  initial
    begin
      $dumpfile("dump.vcd");
      $dumpvars(1, ALU);
    end
  
  always @(*)
  begin
    case(ALU_Sel)
      4'b0000:
        ALU_Res = A+B;
      4'b0001:
        ALU_Res = A-B;
      4'b0010:
        ALU_Res = A*B;
      4'b0011:
        ALU_Res = A/B;
      4'b0100:
        ALU_Res = A << 1;
      4'b0101:
        ALU_Res = A >> 1;
      4'b0110:
        ALU_Res = {A[6:0],A[7]};
      4'b0111:
        ALU_Res = {A[0],A[7:1]};
      4'b1000:
        ALU_Res = A & B;
      4'b1001:
        ALU_Res = A | B;
      4'b1010:
        ALU_Res = A ^ B;
      4'b1011:
        ALU_Res = ~(A|B);
      4'b1100:
        ALU_Res = ~(A&B);
      4'b1101:
        ALU_Res = ~(A^B);
      4'b1110:
        ALU_Res = (A>B)?8'd1:8'd0;
      4'b1111:
        ALU_Res = (A==B)?8'd1:8'd0;
      default:
        ALU_Res = A+B;
    endcase
  end
  
endmodule

testbench.sv
// Code your testbench here
// or browse Examples
module testbench;
  reg[7:0] A,B;
  reg[3:0] ALU_Sel;
  
  wire[7:0] ALU_Out;
  wire CarryOut;
  
  integer i;
  
  ALU alu1(
    A,B,
    ALU_Sel,
    ALU_Out,
    CarryOut
  );
  
  initial
    begin
      A = 8'b00001101;	//13
      B = 8'b00000001;	//1
      ALU_Sel = 4'b0000;
      
      for(i=0;i<=15;i=i+1)
        begin
          #10;
          $display(ALU_Out);
          $display(CarryOut);
          ALU_Sel = ALU_Sel + 4'b0001;
        end
      
    end
endmodule

dump.vcd
$date
	Sat Dec 26 16:01:18 2020
$end
$version
	Icarus Verilog
$end
$timescale
	1s
$end
$scope module testbench $end
$scope module alu1 $end
$var wire 8 ! A [7:0] $end
$var wire 8 " ALU_Out [7:0] $end
$var wire 4 # ALU_Sel [3:0] $end
$var wire 8 $ B [7:0] $end
$var wire 1 % CarryOut $end
$var wire 9 & temp [8:0] $end
$var reg 8 ' ALU_Res [7:0] $end
$upscope $end
$upscope $end
$enddefinitions $end
#0
$dumpvars
b1110 '
b1110 &
0%
b1 $
b0 #
b1110 "
b1101 !
$end
#10
b1100 '
b1100 "
b1 #
#20
b1101 '
b1101 "
b10 #
#30
b11 #
#40
b11010 '
b11010 "
b100 #
#50
b110 '
b110 "
b101 #
#60
b11010 '
b11010 "
b110 #
#70
b10000110 '
b10000110 "
b111 #
#80
b1 '
b1 "
b1000 #
#90
b1101 '
b1101 "
b1001 #
#100
b1100 '
b1100 "
b1010 #
#110
b11110010 '
b11110010 "
b1011 #
#120
b11111110 '
b11111110 "
b1100 #
#130
b11110011 '
b11110011 "
b1101 #
#140
b1 '
b1 "
b1110 #
#150
b0 '
b0 "
b1111 #
#160
b1110 '
b1110 "
b0 #
